{
 "id": "18",
 "previous": "19",
 "next": "19",
 "language": "de",
 "title": "California - Land of Fire?",
 "abstract": "Welche Ursachen haben die Waldbrände in Kalifornien vor dem Hintergrund des Vulnerabilitätsansatzes?  Welche Schäden entstehen durch Waldbrände und Inwiefern können aktuelle Präventionsmanagement und –strategien diese Risiken eindämmen?  Gibt es andere Lösungsansätze?",
 "year": 2020,
 "freidok": "166085",
 "doi": "10.6094/UNIFR/166085",
 "pdf2": "https://freidok.uni-freiburg.de/fedora/objects/freidok:166085/datastreams/FILE1/content",
 "image": "https://freidok.uni-freiburg.de/document/getLogoByPath?mode=freidok&filename=166085_1&mime=png",
 "orientation": "portrait",
 "pdf": "https://globalchanges.github.io/MetaData2020/18/poster.pdf",
 "thumbnail": "https://globalchanges.github.io/MetaData2020/18/thumbnail.png",
 "authors": [
   { 
     "firstname": "Sarah Delphine",
     "name": "Gruner",
     "email": "sarah_gruner@hotmail.de",
     "freidok": "269303",
     "orcid": null
   },
   { 
     "firstname": "Sabine Luzia",
     "name": "Freitag",
     "email": "sabine.freitag@pluto.uni-freiburg.de",
     "freidok": "269304",
     "orcid": null
   }
 ],
 "location": {
   "continent": "Nordamerika",
   "country": "USA",
   "region": "Kalifornien",
   "city": null,
   "landscape": "Küste",
   "latitude": 37.2888262,
   "longitude": -120.153519
 },
 "period": {
    "begin": 1800,
    "end": 2050
 },
 "concept": "Vulnerabel&Resilienz",
 "topic": "Landnutzung",
 "subtopic": "Klimaextreme",
 "keywords": ["Waldbrände","Dürren",""], 
 "sources": [
   {
      "type": "",
      "authors": "",
      "year": 2000,
      "title": "",
      "doi": "",
      "url": "",
      "journal": "",
      "volume": null,
      "publisher": "",
      "pages": ""
   },
   {
      "type": "",
      "authors": "",
      "year": 2000,
      "title": "",
      "doi": "",
      "url": "",
      "journal": "",
      "volume": null,
      "publisher": "",
      "pages": ""
   }
 ]
  


}
